{
  "computed_at": "2026-06-24T16:30:41.104464Z",
  "results": [
    {
      "ticker": "QDVF.DE",
      "display": "QDVF",
      "name": "S&P 500 Energy",
      "bloc": "sector",
      "last_price": 9.848,
      "p1m": -6.76,
      "p3m": -11.39,
      "p6m": 26.01,
      "sma200": 9.1287,
      "above_sma200": true,
      "score": 7.86,
      "error": null
    },
    {
      "ticker": "QDVG.DE",
      "display": "QDVG",
      "name": "S&P 500 Financials",
      "bloc": "sector",
      "last_price": 10.896,
      "p1m": 5.75,
      "p3m": 8.61,
      "p6m": 3.89,
      "sma200": 10.2602,
      "above_sma200": true,
      "score": 18.25,
      "error": null
    },
    {
      "ticker": "QDVH.DE",
      "display": "QDVH",
      "name": "S&P 500 Health Care",
      "bloc": "sector",
      "last_price": 14.082,
      "p1m": 7.04,
      "p3m": 11.87,
      "p6m": 3.04,
      "sma200": 13.2363,
      "above_sma200": true,
      "score": 21.95,
      "error": null
    },
    {
      "ticker": "QDVD.DE",
      "display": "QDVD",
      "name": "S&P 500 Consumer Discret.",
      "bloc": "sector",
      "last_price": 57.45,
      "p1m": 2.53,
      "p3m": 15.27,
      "p6m": 18.03,
      "sma200": 50.6335,
      "above_sma200": true,
      "score": 35.83,
      "error": null
    },
    {
      "ticker": "QDVE.DE",
      "display": "QDVE",
      "name": "S&P 500 Technology",
      "bloc": "sector",
      "last_price": 43.325,
      "p1m": -0.03,
      "p3m": 29.97,
      "p6m": 26.04,
      "sma200": 36.6417,
      "above_sma200": true,
      "score": 55.98,
      "error": null
    },
    {
      "ticker": "QDVC.DE",
      "display": "QDVC",
      "name": "S&P 500 Industrials",
      "bloc": "sector",
      "last_price": 11.732,
      "p1m": 3.62,
      "p3m": 13.35,
      "p6m": 12.27,
      "sma200": 10.6841,
      "above_sma200": true,
      "score": 29.24,
      "error": null
    },
    {
      "ticker": "QDVI.DE",
      "display": "QDVI",
      "name": "MSCI USA Value Factor",
      "bloc": "factor",
      "last_price": 16.606,
      "p1m": 4.74,
      "p3m": 39.62,
      "p6m": 53.39,
      "sma200": 12.0937,
      "above_sma200": true,
      "score": 97.75,
      "error": null
    },
    {
      "ticker": "IWMO.L",
      "display": "IWMO",
      "name": "MSCI World Momentum",
      "bloc": "factor",
      "last_price": 120.05,
      "p1m": 2.7,
      "p3m": 27.25,
      "p6m": 23.83,
      "sma200": 101.1827,
      "above_sma200": true,
      "score": 53.78,
      "error": null
    },
    {
      "ticker": "IWQU.L",
      "display": "IWQU",
      "name": "MSCI World Quality",
      "bloc": "factor",
      "last_price": 86.11,
      "p1m": -0.57,
      "p3m": 9.78,
      "p6m": 8.3,
      "sma200": 80.9282,
      "above_sma200": true,
      "score": 17.51,
      "error": null
    },
    {
      "ticker": "WSML.L",
      "display": "WSML",
      "name": "MSCI World Small Cap",
      "bloc": "factor",
      "last_price": 10.382,
      "p1m": 0.7,
      "p3m": 13.23,
      "p6m": 14.25,
      "sma200": 9.4224,
      "above_sma200": true,
      "score": 28.18,
      "error": null
    },
    {
      "ticker": "MVOL.L",
      "display": "MVOL",
      "name": "MSCI World Min Volatility",
      "bloc": "factor",
      "last_price": 73.48,
      "p1m": -1.25,
      "p3m": 0.48,
      "p6m": 0.38,
      "sma200": 73.6976,
      "above_sma200": false,
      "score": -0.39,
      "error": null
    },
    {
      "ticker": "IEMA.L",
      "display": "IEMA",
      "name": "MSCI Emerging Markets",
      "bloc": "refuge",
      "last_price": 64.7,
      "p1m": -0.66,
      "p3m": 19.13,
      "p6m": 25.83,
      "sma200": 55.9142,
      "above_sma200": true,
      "score": 44.3,
      "error": null
    },
    {
      "ticker": "IGLN.L",
      "display": "IGLN",
      "name": "Physical Gold ETC",
      "bloc": "refuge",
      "last_price": 77.76,
      "p1m": -11.03,
      "p3m": -8.52,
      "p6m": -7.85,
      "sma200": 86.4033,
      "above_sma200": false,
      "score": -27.4,
      "error": null
    },
    {
      "ticker": "IDTM.L",
      "display": "IDTM",
      "name": "US Treasuries 7-10Y",
      "bloc": "refuge",
      "last_price": 171.39,
      "p1m": 0.91,
      "p3m": 0.69,
      "p6m": 0.11,
      "sma200": 171.0585,
      "above_sma200": true,
      "score": 1.71,
      "error": null
    }
  ]
}